{
  "2026-01-01": {
    "tiles": [
      1,
      2,
      3,
      4,
      5,
      6,
      7,
      8,
      9,
      10,
      11,
      12
    ],
    "seed": "delta-node-45",
    "difficulty": "Hard"
  },
  "2026-01-02": {
    "tiles": [
      1,
      2,
      3,
      4,
      5,
      6,
      7,
      8,
      9
    ],
    "seed": "omega-omega-82",
    "difficulty": "Normal"
  },
  "2026-01-03": {
    "tiles": [
      1,
      2,
      3,
      4,
      5,
      6,
      7,
      8,
      9,
      10,
      11,
      12
    ],
    "seed": "alpha-sun-74",
    "difficulty": "Hard"
  },
  "2026-01-04": {
    "tiles": [
      1,
      2,
      3,
      4,
      5,
      6,
      7,
      8,
      9
    ],
    "seed": "zero-core-37",
    "difficulty": "Normal"
  },
  "2026-01-05": {
    "tiles": [
      1,
      2,
      3,
      4,
      5,
      6,
      7,
      8,
      9,
      10,
      11,
      12
    ],
    "seed": "delta-sun-61",
    "difficulty": "Hard"
  },
  "2026-01-06": {
    "tiles": [
      1,
      2,
      3,
      4,
      5,
      6,
      7,
      8,
      9
    ],
    "seed": "nova-sun-78",
    "difficulty": "Normal"
  },
  "2026-01-07": {
    "tiles": [
      1,
      2,
      3,
      4,
      5,
      6,
      7,
      8,
      9,
      10,
      11,
      12
    ],
    "seed": "omega-prime-78",
    "difficulty": "Hard"
  },
  "2026-01-08": {
    "tiles": [
      1,
      2,
      3,
      4,
      5,
      6,
      7,
      8,
      9
    ],
    "seed": "delta-pulse-39",
    "difficulty": "Normal"
  },
  "2026-01-09": {
    "tiles": [
      1,
      2,
      3,
      4,
      5,
      6,
      7,
      8,
      9,
      10,
      11,
      12
    ],
    "seed": "solar-omega-59",
    "difficulty": "Hard"
  },
  "2026-01-10": {
    "tiles": [
      1,
      2,
      3,
      4,
      5,
      6,
      7,
      8,
      9
    ],
    "seed": "delta-moon-32",
    "difficulty": "Normal"
  },
  "2026-01-11": {
    "tiles": [
      1,
      2,
      3,
      4,
      5,
      6,
      7,
      8,
      9,
      10,
      11,
      12
    ],
    "seed": "delta-prime-71",
    "difficulty": "Hard"
  },
  "2026-01-12": {
    "tiles": [
      1,
      2,
      3,
      4,
      5,
      6,
      7,
      8,
      9
    ],
    "seed": "delta-pulse-63",
    "difficulty": "Normal"
  },
  "2026-01-13": {
    "tiles": [
      1,
      2,
      3,
      4,
      5,
      6,
      7,
      8,
      9,
      10,
      11,
      12
    ],
    "seed": "alpha-star-23",
    "difficulty": "Hard"
  },
  "2026-01-14": {
    "tiles": [
      1,
      2,
      3,
      4,
      5,
      6,
      7,
      8,
      9
    ],
    "seed": "alpha-omega-23",
    "difficulty": "Normal"
  },
  "2026-01-15": {
    "tiles": [
      1,
      2,
      3,
      4,
      5,
      6,
      7,
      8,
      9,
      10,
      11,
      12
    ],
    "seed": "gamma-star-61",
    "difficulty": "Hard"
  },
  "2026-01-16": {
    "tiles": [
      1,
      2,
      3,
      4,
      5,
      6,
      7,
      8,
      9
    ],
    "seed": "nova-node-73",
    "difficulty": "Normal"
  },
  "2026-01-17": {
    "tiles": [
      1,
      2,
      3,
      4,
      5,
      6,
      7,
      8,
      9,
      10,
      11,
      12
    ],
    "seed": "gamma-sun-32",
    "difficulty": "Hard"
  },
  "2026-01-18": {
    "tiles": [
      1,
      2,
      3,
      4,
      5,
      6,
      7,
      8,
      9
    ],
    "seed": "alpha-moon-38",
    "difficulty": "Normal"
  },
  "2026-01-19": {
    "tiles": [
      1,
      2,
      3,
      4,
      5,
      6,
      7,
      8,
      9,
      10,
      11,
      12
    ],
    "seed": "lunar-moon-49",
    "difficulty": "Hard"
  },
  "2026-01-20": {
    "tiles": [
      1,
      2,
      3,
      4,
      5,
      6,
      7,
      8,
      9
    ],
    "seed": "gamma-star-21",
    "difficulty": "Normal"
  },
  "2026-01-21": {
    "tiles": [
      1,
      2,
      3,
      4,
      5,
      6,
      7,
      8,
      9,
      10,
      11,
      12
    ],
    "seed": "prime-prime-90",
    "difficulty": "Hard"
  },
  "2026-01-22": {
    "tiles": [
      1,
      2,
      3,
      4,
      5,
      6,
      7,
      8,
      9
    ],
    "seed": "zero-wave-38",
    "difficulty": "Normal"
  },
  "2026-01-23": {
    "tiles": [
      1,
      2,
      3,
      4,
      5,
      6,
      7,
      8,
      9,
      10,
      11,
      12
    ],
    "seed": "gamma-omega-35",
    "difficulty": "Hard"
  },
  "2026-01-24": {
    "tiles": [
      1,
      2,
      3,
      4,
      5,
      6,
      7,
      8,
      9
    ],
    "seed": "prime-star-35",
    "difficulty": "Normal"
  },
  "2026-01-25": {
    "tiles": [
      1,
      2,
      3,
      4,
      5,
      6,
      7,
      8,
      9,
      10,
      11,
      12
    ],
    "seed": "zero-prime-88",
    "difficulty": "Hard"
  },
  "2026-01-26": {
    "tiles": [
      1,
      2,
      3,
      4,
      5,
      6,
      7,
      8,
      9
    ],
    "seed": "gamma-node-91",
    "difficulty": "Normal"
  },
  "2026-01-27": {
    "tiles": [
      1,
      2,
      3,
      4,
      5,
      6,
      7,
      8,
      9,
      10,
      11,
      12
    ],
    "seed": "alpha-prime-61",
    "difficulty": "Hard"
  },
  "2026-01-28": {
    "tiles": [
      1,
      2,
      3,
      4,
      5,
      6,
      7,
      8,
      9
    ],
    "seed": "prime-pulse-69",
    "difficulty": "Normal"
  },
  "2026-01-29": {
    "tiles": [
      1,
      2,
      3,
      4,
      5,
      6,
      7,
      8,
      9,
      10,
      11,
      12
    ],
    "seed": "nova-wave-18",
    "difficulty": "Hard"
  },
  "2026-01-30": {
    "tiles": [
      1,
      2,
      3,
      4,
      5,
      6,
      7,
      8,
      9
    ],
    "seed": "gamma-moon-15",
    "difficulty": "Normal"
  },
  "2026-01-31": {
    "tiles": [
      1,
      2,
      3,
      4,
      5,
      6,
      7,
      8,
      9,
      10,
      11,
      12
    ],
    "seed": "lunar-core-74",
    "difficulty": "Hard"
  },
  "2026-02-01": {
    "tiles": [
      1,
      2,
      3,
      4,
      5,
      6,
      7,
      8,
      9
    ],
    "seed": "prime-star-24",
    "difficulty": "Normal"
  },
  "2026-02-02": {
    "tiles": [
      1,
      2,
      3,
      4,
      5,
      6,
      7,
      8,
      9,
      10,
      11,
      12
    ],
    "seed": "solar-omega-22",
    "difficulty": "Hard"
  },
  "2026-02-03": {
    "tiles": [
      1,
      2,
      3,
      4,
      5,
      6,
      7,
      8,
      9
    ],
    "seed": "lunar-star-91",
    "difficulty": "Normal"
  },
  "2026-02-04": {
    "tiles": [
      1,
      2,
      3,
      4,
      5,
      6,
      7,
      8,
      9,
      10,
      11,
      12
    ],
    "seed": "gamma-prime-16",
    "difficulty": "Hard"
  },
  "2026-02-05": {
    "tiles": [
      1,
      2,
      3,
      4,
      5,
      6,
      7,
      8,
      9
    ],
    "seed": "nova-prime-99",
    "difficulty": "Normal"
  },
  "2026-02-06": {
    "tiles": [
      1,
      2,
      3,
      4,
      5,
      6,
      7,
      8,
      9,
      10,
      11,
      12
    ],
    "seed": "prime-flux-40",
    "difficulty": "Hard"
  },
  "2026-02-07": {
    "tiles": [
      1,
      2,
      3,
      4,
      5,
      6,
      7,
      8,
      9
    ],
    "seed": "nova-star-74",
    "difficulty": "Normal"
  },
  "2026-02-08": {
    "tiles": [
      1,
      2,
      3,
      4,
      5,
      6,
      7,
      8,
      9,
      10,
      11,
      12
    ],
    "seed": "omega-prime-65",
    "difficulty": "Hard"
  },
  "2026-02-09": {
    "tiles": [
      1,
      2,
      3,
      4,
      5,
      6,
      7,
      8,
      9
    ],
    "seed": "prime-sun-88",
    "difficulty": "Normal"
  },
  "2026-02-10": {
    "tiles": [
      1,
      2,
      3,
      4,
      5,
      6,
      7,
      8,
      9,
      10,
      11,
      12
    ],
    "seed": "delta-sun-82",
    "difficulty": "Hard"
  },
  "2026-02-11": {
    "tiles": [
      1,
      2,
      3,
      4,
      5,
      6,
      7,
      8,
      9
    ],
    "seed": "gamma-sun-22",
    "difficulty": "Normal"
  },
  "2026-02-12": {
    "tiles": [
      1,
      2,
      3,
      4,
      5,
      6,
      7,
      8,
      9,
      10,
      11,
      12
    ],
    "seed": "zero-flux-93",
    "difficulty": "Hard"
  },
  "2026-02-13": {
    "tiles": [
      1,
      2,
      3,
      4,
      5,
      6,
      7,
      8,
      9
    ],
    "seed": "nova-core-33",
    "difficulty": "Normal"
  },
  "2026-02-14": {
    "tiles": [
      1,
      2,
      3,
      4,
      5,
      6,
      7,
      8,
      9,
      10,
      11,
      12
    ],
    "seed": "gamma-core-37",
    "difficulty": "Hard"
  },
  "2026-02-15": {
    "tiles": [
      1,
      2,
      3,
      4,
      5,
      6,
      7,
      8,
      9
    ],
    "seed": "gamma-prime-54",
    "difficulty": "Normal"
  },
  "2026-02-16": {
    "tiles": [
      1,
      2,
      3,
      4,
      5,
      6,
      7,
      8,
      9,
      10,
      11,
      12
    ],
    "seed": "solar-prime-51",
    "difficulty": "Hard"
  },
  "2026-02-17": {
    "tiles": [
      1,
      2,
      3,
      4,
      5,
      6,
      7,
      8,
      9
    ],
    "seed": "solar-flux-26",
    "difficulty": "Normal"
  },
  "2026-02-18": {
    "tiles": [
      1,
      2,
      3,
      4,
      5,
      6,
      7,
      8,
      9,
      10,
      11,
      12
    ],
    "seed": "zero-omega-98",
    "difficulty": "Hard"
  },
  "2026-02-19": {
    "tiles": [
      1,
      2,
      3,
      4,
      5,
      6,
      7,
      8,
      9
    ],
    "seed": "zero-wave-60",
    "difficulty": "Normal"
  },
  "2026-02-20": {
    "tiles": [
      1,
      2,
      3,
      4,
      5,
      6,
      7,
      8,
      9,
      10,
      11,
      12
    ],
    "seed": "delta-omega-20",
    "difficulty": "Hard"
  },
  "2026-02-21": {
    "tiles": [
      1,
      2,
      3,
      4,
      5,
      6,
      7,
      8,
      9
    ],
    "seed": "prime-flux-37",
    "difficulty": "Normal"
  },
  "2026-02-22": {
    "tiles": [
      1,
      2,
      3,
      4,
      5,
      6,
      7,
      8,
      9,
      10,
      11,
      12
    ],
    "seed": "beta-pulse-76",
    "difficulty": "Hard"
  },
  "2026-02-23": {
    "tiles": [
      1,
      2,
      3,
      4,
      5,
      6,
      7,
      8,
      9
    ],
    "seed": "gamma-omega-81",
    "difficulty": "Normal"
  },
  "2026-02-24": {
    "tiles": [
      1,
      2,
      3,
      4,
      5,
      6,
      7,
      8,
      9,
      10,
      11,
      12
    ],
    "seed": "nova-star-15",
    "difficulty": "Hard"
  },
  "2026-02-25": {
    "tiles": [
      1,
      2,
      3,
      4,
      5,
      6,
      7,
      8,
      9
    ],
    "seed": "lunar-flux-40",
    "difficulty": "Normal"
  },
  "2026-02-26": {
    "tiles": [
      1,
      2,
      3,
      4,
      5,
      6,
      7,
      8,
      9,
      10,
      11,
      12
    ],
    "seed": "solar-core-88",
    "difficulty": "Hard"
  },
  "2026-02-27": {
    "tiles": [
      1,
      2,
      3,
      4,
      5,
      6,
      7,
      8,
      9
    ],
    "seed": "beta-node-68",
    "difficulty": "Normal"
  },
  "2026-02-28": {
    "tiles": [
      1,
      2,
      3,
      4,
      5,
      6,
      7,
      8,
      9,
      10,
      11,
      12
    ],
    "seed": "lunar-moon-68",
    "difficulty": "Hard"
  },
  "2026-03-01": {
    "tiles": [
      1,
      2,
      3,
      4,
      5,
      6,
      7,
      8,
      9
    ],
    "seed": "gamma-core-45",
    "difficulty": "Normal"
  },
  "2026-03-02": {
    "tiles": [
      1,
      2,
      3,
      4,
      5,
      6,
      7,
      8,
      9,
      10,
      11,
      12
    ],
    "seed": "beta-moon-33",
    "difficulty": "Hard"
  },
  "2026-03-03": {
    "tiles": [
      1,
      2,
      3,
      4,
      5,
      6,
      7,
      8,
      9
    ],
    "seed": "prime-wave-70",
    "difficulty": "Normal"
  },
  "2026-03-04": {
    "tiles": [
      1,
      2,
      3,
      4,
      5,
      6,
      7,
      8,
      9,
      10,
      11,
      12
    ],
    "seed": "delta-omega-53",
    "difficulty": "Hard"
  },
  "2026-03-05": {
    "tiles": [
      1,
      2,
      3,
      4,
      5,
      6,
      7,
      8,
      9
    ],
    "seed": "omega-omega-34",
    "difficulty": "Normal"
  },
  "2026-03-06": {
    "tiles": [
      1,
      2,
      3,
      4,
      5,
      6,
      7,
      8,
      9,
      10,
      11,
      12
    ],
    "seed": "nova-flux-55",
    "difficulty": "Hard"
  },
  "2026-03-07": {
    "tiles": [
      1,
      2,
      3,
      4,
      5,
      6,
      7,
      8,
      9
    ],
    "seed": "delta-sun-87",
    "difficulty": "Normal"
  },
  "2026-03-08": {
    "tiles": [
      1,
      2,
      3,
      4,
      5,
      6,
      7,
      8,
      9,
      10,
      11,
      12
    ],
    "seed": "omega-moon-78",
    "difficulty": "Hard"
  },
  "2026-03-09": {
    "tiles": [
      1,
      2,
      3,
      4,
      5,
      6,
      7,
      8,
      9
    ],
    "seed": "prime-pulse-65",
    "difficulty": "Normal"
  },
  "2026-03-10": {
    "tiles": [
      1,
      2,
      3,
      4,
      5,
      6,
      7,
      8,
      9,
      10,
      11,
      12
    ],
    "seed": "lunar-prime-63",
    "difficulty": "Hard"
  },
  "2026-03-11": {
    "tiles": [
      1,
      2,
      3,
      4,
      5,
      6,
      7,
      8,
      9
    ],
    "seed": "lunar-sun-59",
    "difficulty": "Normal"
  },
  "2026-03-12": {
    "tiles": [
      1,
      2,
      3,
      4,
      5,
      6,
      7,
      8,
      9,
      10,
      11,
      12
    ],
    "seed": "delta-prime-20",
    "difficulty": "Hard"
  },
  "2026-03-13": {
    "tiles": [
      1,
      2,
      3,
      4,
      5,
      6,
      7,
      8,
      9
    ],
    "seed": "beta-core-78",
    "difficulty": "Normal"
  },
  "2026-03-14": {
    "tiles": [
      1,
      2,
      3,
      4,
      5,
      6,
      7,
      8,
      9,
      10,
      11,
      12
    ],
    "seed": "delta-prime-76",
    "difficulty": "Hard"
  },
  "2026-03-15": {
    "tiles": [
      1,
      2,
      3,
      4,
      5,
      6,
      7,
      8,
      9
    ],
    "seed": "prime-star-16",
    "difficulty": "Normal"
  },
  "2026-03-16": {
    "tiles": [
      1,
      2,
      3,
      4,
      5,
      6,
      7,
      8,
      9,
      10,
      11,
      12
    ],
    "seed": "prime-core-27",
    "difficulty": "Hard"
  },
  "2026-03-17": {
    "tiles": [
      1,
      2,
      3,
      4,
      5,
      6,
      7,
      8,
      9
    ],
    "seed": "lunar-flux-62",
    "difficulty": "Normal"
  },
  "2026-03-18": {
    "tiles": [
      1,
      2,
      3,
      4,
      5,
      6,
      7,
      8,
      9,
      10,
      11,
      12
    ],
    "seed": "lunar-flux-50",
    "difficulty": "Hard"
  },
  "2026-03-19": {
    "tiles": [
      1,
      2,
      3,
      4,
      5,
      6,
      7,
      8,
      9
    ],
    "seed": "omega-prime-40",
    "difficulty": "Normal"
  },
  "2026-03-20": {
    "tiles": [
      1,
      2,
      3,
      4,
      5,
      6,
      7,
      8,
      9,
      10,
      11,
      12
    ],
    "seed": "nova-star-99",
    "difficulty": "Hard"
  },
  "2026-03-21": {
    "tiles": [
      1,
      2,
      3,
      4,
      5,
      6,
      7,
      8,
      9
    ],
    "seed": "solar-star-96",
    "difficulty": "Normal"
  },
  "2026-03-22": {
    "tiles": [
      1,
      2,
      3,
      4,
      5,
      6,
      7,
      8,
      9,
      10,
      11,
      12
    ],
    "seed": "lunar-moon-69",
    "difficulty": "Hard"
  },
  "2026-03-23": {
    "tiles": [
      1,
      2,
      3,
      4,
      5,
      6,
      7,
      8,
      9
    ],
    "seed": "delta-flux-81",
    "difficulty": "Normal"
  },
  "2026-03-24": {
    "tiles": [
      1,
      2,
      3,
      4,
      5,
      6,
      7,
      8,
      9,
      10,
      11,
      12
    ],
    "seed": "prime-prime-45",
    "difficulty": "Hard"
  },
  "2026-03-25": {
    "tiles": [
      1,
      2,
      3,
      4,
      5,
      6,
      7,
      8,
      9
    ],
    "seed": "gamma-core-91",
    "difficulty": "Normal"
  },
  "2026-03-26": {
    "tiles": [
      1,
      2,
      3,
      4,
      5,
      6,
      7,
      8,
      9,
      10,
      11,
      12
    ],
    "seed": "beta-prime-23",
    "difficulty": "Hard"
  },
  "2026-03-27": {
    "tiles": [
      1,
      2,
      3,
      4,
      5,
      6,
      7,
      8,
      9
    ],
    "seed": "gamma-omega-53",
    "difficulty": "Normal"
  },
  "2026-03-28": {
    "tiles": [
      1,
      2,
      3,
      4,
      5,
      6,
      7,
      8,
      9,
      10,
      11,
      12
    ],
    "seed": "lunar-omega-44",
    "difficulty": "Hard"
  },
  "2026-03-29": {
    "tiles": [
      1,
      2,
      3,
      4,
      5,
      6,
      7,
      8,
      9
    ],
    "seed": "lunar-wave-21",
    "difficulty": "Normal"
  },
  "2026-03-30": {
    "tiles": [
      1,
      2,
      3,
      4,
      5,
      6,
      7,
      8,
      9,
      10,
      11,
      12
    ],
    "seed": "nova-flux-13",
    "difficulty": "Hard"
  },
  "2026-03-31": {
    "tiles": [
      1,
      2,
      3,
      4,
      5,
      6,
      7,
      8,
      9
    ],
    "seed": "gamma-star-90",
    "difficulty": "Normal"
  },
  "2026-04-01": {
    "tiles": [
      1,
      2,
      3,
      4,
      5,
      6,
      7,
      8,
      9,
      10,
      11,
      12
    ],
    "seed": "omega-star-71",
    "difficulty": "Hard"
  },
  "2026-04-02": {
    "tiles": [
      1,
      2,
      3,
      4,
      5,
      6,
      7,
      8,
      9
    ],
    "seed": "alpha-pulse-60",
    "difficulty": "Normal"
  },
  "2026-04-03": {
    "tiles": [
      1,
      2,
      3,
      4,
      5,
      6,
      7,
      8,
      9,
      10,
      11,
      12
    ],
    "seed": "prime-node-76",
    "difficulty": "Hard"
  },
  "2026-04-04": {
    "tiles": [
      1,
      2,
      3,
      4,
      5,
      6,
      7,
      8,
      9
    ],
    "seed": "alpha-sun-52",
    "difficulty": "Normal"
  },
  "2026-04-05": {
    "tiles": [
      1,
      2,
      3,
      4,
      5,
      6,
      7,
      8,
      9,
      10,
      11,
      12
    ],
    "seed": "alpha-moon-74",
    "difficulty": "Hard"
  },
  "2026-04-06": {
    "tiles": [
      1,
      2,
      3,
      4,
      5,
      6,
      7,
      8,
      9
    ],
    "seed": "lunar-pulse-64",
    "difficulty": "Normal"
  },
  "2026-04-07": {
    "tiles": [
      1,
      2,
      3,
      4,
      5,
      6,
      7,
      8,
      9,
      10,
      11,
      12
    ],
    "seed": "alpha-prime-39",
    "difficulty": "Hard"
  },
  "2026-04-08": {
    "tiles": [
      1,
      2,
      3,
      4,
      5,
      6,
      7,
      8,
      9
    ],
    "seed": "zero-flux-10",
    "difficulty": "Normal"
  },
  "2026-04-09": {
    "tiles": [
      1,
      2,
      3,
      4,
      5,
      6,
      7,
      8,
      9,
      10,
      11,
      12
    ],
    "seed": "gamma-star-40",
    "difficulty": "Hard"
  },
  "2026-04-10": {
    "tiles": [
      1,
      2,
      3,
      4,
      5,
      6,
      7,
      8,
      9
    ],
    "seed": "beta-node-53",
    "difficulty": "Normal"
  },
  "2026-04-11": {
    "tiles": [
      1,
      2,
      3,
      4,
      5,
      6,
      7,
      8,
      9,
      10,
      11,
      12
    ],
    "seed": "prime-sun-36",
    "difficulty": "Hard"
  },
  "2026-04-12": {
    "tiles": [
      1,
      2,
      3,
      4,
      5,
      6,
      7,
      8,
      9
    ],
    "seed": "alpha-flux-26",
    "difficulty": "Normal"
  },
  "2026-04-13": {
    "tiles": [
      1,
      2,
      3,
      4,
      5,
      6,
      7,
      8,
      9,
      10,
      11,
      12
    ],
    "seed": "lunar-sun-27",
    "difficulty": "Hard"
  },
  "2026-04-14": {
    "tiles": [
      1,
      2,
      3,
      4,
      5,
      6,
      7,
      8,
      9
    ],
    "seed": "lunar-pulse-61",
    "difficulty": "Normal"
  },
  "2026-04-15": {
    "tiles": [
      1,
      2,
      3,
      4,
      5,
      6,
      7,
      8,
      9,
      10,
      11,
      12
    ],
    "seed": "lunar-core-74",
    "difficulty": "Hard"
  },
  "2026-04-16": {
    "tiles": [
      1,
      2,
      3,
      4,
      5,
      6,
      7,
      8,
      9
    ],
    "seed": "zero-moon-23",
    "difficulty": "Normal"
  },
  "2026-04-17": {
    "tiles": [
      1,
      2,
      3,
      4,
      5,
      6,
      7,
      8,
      9,
      10,
      11,
      12
    ],
    "seed": "prime-moon-91",
    "difficulty": "Hard"
  },
  "2026-04-18": {
    "tiles": [
      1,
      2,
      3,
      4,
      5,
      6,
      7,
      8,
      9
    ],
    "seed": "lunar-sun-85",
    "difficulty": "Normal"
  },
  "2026-04-19": {
    "tiles": [
      1,
      2,
      3,
      4,
      5,
      6,
      7,
      8,
      9,
      10,
      11,
      12
    ],
    "seed": "zero-flux-57",
    "difficulty": "Hard"
  },
  "2026-04-20": {
    "tiles": [
      1,
      2,
      3,
      4,
      5,
      6,
      7,
      8,
      9
    ],
    "seed": "prime-core-59",
    "difficulty": "Normal"
  },
  "2026-04-21": {
    "tiles": [
      1,
      2,
      3,
      4,
      5,
      6,
      7,
      8,
      9,
      10,
      11,
      12
    ],
    "seed": "beta-core-74",
    "difficulty": "Hard"
  },
  "2026-04-22": {
    "tiles": [
      1,
      2,
      3,
      4,
      5,
      6,
      7,
      8,
      9
    ],
    "seed": "delta-moon-54",
    "difficulty": "Normal"
  },
  "2026-04-23": {
    "tiles": [
      1,
      2,
      3,
      4,
      5,
      6,
      7,
      8,
      9,
      10,
      11,
      12
    ],
    "seed": "prime-core-37",
    "difficulty": "Hard"
  },
  "2026-04-24": {
    "tiles": [
      1,
      2,
      3,
      4,
      5,
      6,
      7,
      8,
      9
    ],
    "seed": "solar-flux-21",
    "difficulty": "Normal"
  },
  "2026-04-25": {
    "tiles": [
      1,
      2,
      3,
      4,
      5,
      6,
      7,
      8,
      9,
      10,
      11,
      12
    ],
    "seed": "gamma-wave-19",
    "difficulty": "Hard"
  },
  "2026-04-26": {
    "tiles": [
      1,
      2,
      3,
      4,
      5,
      6,
      7,
      8,
      9
    ],
    "seed": "delta-pulse-15",
    "difficulty": "Normal"
  },
  "2026-04-27": {
    "tiles": [
      1,
      2,
      3,
      4,
      5,
      6,
      7,
      8,
      9,
      10,
      11,
      12
    ],
    "seed": "delta-pulse-64",
    "difficulty": "Hard"
  },
  "2026-04-28": {
    "tiles": [
      1,
      2,
      3,
      4,
      5,
      6,
      7,
      8,
      9
    ],
    "seed": "nova-core-36",
    "difficulty": "Normal"
  },
  "2026-04-29": {
    "tiles": [
      1,
      2,
      3,
      4,
      5,
      6,
      7,
      8,
      9,
      10,
      11,
      12
    ],
    "seed": "solar-omega-12",
    "difficulty": "Hard"
  },
  "2026-04-30": {
    "tiles": [
      1,
      2,
      3,
      4,
      5,
      6,
      7,
      8,
      9
    ],
    "seed": "omega-star-39",
    "difficulty": "Normal"
  },
  "2026-05-01": {
    "tiles": [
      1,
      2,
      3,
      4,
      5,
      6,
      7,
      8,
      9,
      10,
      11,
      12
    ],
    "seed": "prime-node-80",
    "difficulty": "Hard"
  },
  "2026-05-02": {
    "tiles": [
      1,
      2,
      3,
      4,
      5,
      6,
      7,
      8,
      9
    ],
    "seed": "solar-flux-41",
    "difficulty": "Normal"
  },
  "2026-05-03": {
    "tiles": [
      1,
      2,
      3,
      4,
      5,
      6,
      7,
      8,
      9,
      10,
      11,
      12
    ],
    "seed": "omega-moon-78",
    "difficulty": "Hard"
  },
  "2026-05-04": {
    "tiles": [
      1,
      2,
      3,
      4,
      5,
      6,
      7,
      8,
      9
    ],
    "seed": "prime-pulse-74",
    "difficulty": "Normal"
  },
  "2026-05-05": {
    "tiles": [
      1,
      2,
      3,
      4,
      5,
      6,
      7,
      8,
      9,
      10,
      11,
      12
    ],
    "seed": "zero-flux-56",
    "difficulty": "Hard"
  },
  "2026-05-06": {
    "tiles": [
      1,
      2,
      3,
      4,
      5,
      6,
      7,
      8,
      9
    ],
    "seed": "prime-moon-72",
    "difficulty": "Normal"
  },
  "2026-05-07": {
    "tiles": [
      1,
      2,
      3,
      4,
      5,
      6,
      7,
      8,
      9,
      10,
      11,
      12
    ],
    "seed": "beta-sun-21",
    "difficulty": "Hard"
  },
  "2026-05-08": {
    "tiles": [
      1,
      2,
      3,
      4,
      5,
      6,
      7,
      8,
      9
    ],
    "seed": "delta-prime-26",
    "difficulty": "Normal"
  },
  "2026-05-09": {
    "tiles": [
      1,
      2,
      3,
      4,
      5,
      6,
      7,
      8,
      9,
      10,
      11,
      12
    ],
    "seed": "beta-omega-84",
    "difficulty": "Hard"
  },
  "2026-05-10": {
    "tiles": [
      1,
      2,
      3,
      4,
      5,
      6,
      7,
      8,
      9
    ],
    "seed": "beta-node-78",
    "difficulty": "Normal"
  },
  "2026-05-11": {
    "tiles": [
      1,
      2,
      3,
      4,
      5,
      6,
      7,
      8,
      9,
      10,
      11,
      12
    ],
    "seed": "omega-sun-29",
    "difficulty": "Hard"
  },
  "2026-05-12": {
    "tiles": [
      1,
      2,
      3,
      4,
      5,
      6,
      7,
      8,
      9
    ],
    "seed": "lunar-node-72",
    "difficulty": "Normal"
  },
  "2026-05-13": {
    "tiles": [
      1,
      2,
      3,
      4,
      5,
      6,
      7,
      8,
      9,
      10,
      11,
      12
    ],
    "seed": "beta-omega-71",
    "difficulty": "Hard"
  },
  "2026-05-14": {
    "tiles": [
      1,
      2,
      3,
      4,
      5,
      6,
      7,
      8,
      9
    ],
    "seed": "alpha-node-46",
    "difficulty": "Normal"
  },
  "2026-05-15": {
    "tiles": [
      1,
      2,
      3,
      4,
      5,
      6,
      7,
      8,
      9,
      10,
      11,
      12
    ],
    "seed": "beta-flux-81",
    "difficulty": "Hard"
  },
  "2026-05-16": {
    "tiles": [
      1,
      2,
      3,
      4,
      5,
      6,
      7,
      8,
      9
    ],
    "seed": "alpha-moon-68",
    "difficulty": "Normal"
  },
  "2026-05-17": {
    "tiles": [
      1,
      2,
      3,
      4,
      5,
      6,
      7,
      8,
      9,
      10,
      11,
      12
    ],
    "seed": "nova-sun-13",
    "difficulty": "Hard"
  },
  "2026-05-18": {
    "tiles": [
      1,
      2,
      3,
      4,
      5,
      6,
      7,
      8,
      9
    ],
    "seed": "omega-moon-79",
    "difficulty": "Normal"
  },
  "2026-05-19": {
    "tiles": [
      1,
      2,
      3,
      4,
      5,
      6,
      7,
      8,
      9,
      10,
      11,
      12
    ],
    "seed": "solar-flux-83",
    "difficulty": "Hard"
  },
  "2026-05-20": {
    "tiles": [
      1,
      2,
      3,
      4,
      5,
      6,
      7,
      8,
      9
    ],
    "seed": "gamma-pulse-12",
    "difficulty": "Normal"
  },
  "2026-05-21": {
    "tiles": [
      1,
      2,
      3,
      4,
      5,
      6,
      7,
      8,
      9,
      10,
      11,
      12
    ],
    "seed": "lunar-omega-17",
    "difficulty": "Hard"
  },
  "2026-05-22": {
    "tiles": [
      1,
      2,
      3,
      4,
      5,
      6,
      7,
      8,
      9
    ],
    "seed": "gamma-prime-88",
    "difficulty": "Normal"
  },
  "2026-05-23": {
    "tiles": [
      1,
      2,
      3,
      4,
      5,
      6,
      7,
      8,
      9,
      10,
      11,
      12
    ],
    "seed": "nova-prime-60",
    "difficulty": "Hard"
  },
  "2026-05-24": {
    "tiles": [
      1,
      2,
      3,
      4,
      5,
      6,
      7,
      8,
      9
    ],
    "seed": "solar-moon-62",
    "difficulty": "Normal"
  },
  "2026-05-25": {
    "tiles": [
      1,
      2,
      3,
      4,
      5,
      6,
      7,
      8,
      9,
      10,
      11,
      12
    ],
    "seed": "omega-moon-86",
    "difficulty": "Hard"
  },
  "2026-05-26": {
    "tiles": [
      1,
      2,
      3,
      4,
      5,
      6,
      7,
      8,
      9
    ],
    "seed": "solar-sun-27",
    "difficulty": "Normal"
  },
  "2026-05-27": {
    "tiles": [
      1,
      2,
      3,
      4,
      5,
      6,
      7,
      8,
      9,
      10,
      11,
      12
    ],
    "seed": "lunar-sun-87",
    "difficulty": "Hard"
  },
  "2026-05-28": {
    "tiles": [
      1,
      2,
      3,
      4,
      5,
      6,
      7,
      8,
      9
    ],
    "seed": "lunar-prime-28",
    "difficulty": "Normal"
  },
  "2026-05-29": {
    "tiles": [
      1,
      2,
      3,
      4,
      5,
      6,
      7,
      8,
      9,
      10,
      11,
      12
    ],
    "seed": "delta-node-80",
    "difficulty": "Hard"
  },
  "2026-05-30": {
    "tiles": [
      1,
      2,
      3,
      4,
      5,
      6,
      7,
      8,
      9
    ],
    "seed": "solar-core-78",
    "difficulty": "Normal"
  },
  "2026-05-31": {
    "tiles": [
      1,
      2,
      3,
      4,
      5,
      6,
      7,
      8,
      9,
      10,
      11,
      12
    ],
    "seed": "nova-pulse-45",
    "difficulty": "Hard"
  },
  "2026-06-01": {
    "tiles": [
      1,
      2,
      3,
      4,
      5,
      6,
      7,
      8,
      9
    ],
    "seed": "zero-sun-80",
    "difficulty": "Normal"
  },
  "2026-06-02": {
    "tiles": [
      1,
      2,
      3,
      4,
      5,
      6,
      7,
      8,
      9,
      10,
      11,
      12
    ],
    "seed": "alpha-prime-26",
    "difficulty": "Hard"
  },
  "2026-06-03": {
    "tiles": [
      1,
      2,
      3,
      4,
      5,
      6,
      7,
      8,
      9
    ],
    "seed": "beta-flux-29",
    "difficulty": "Normal"
  },
  "2026-06-04": {
    "tiles": [
      1,
      2,
      3,
      4,
      5,
      6,
      7,
      8,
      9,
      10,
      11,
      12
    ],
    "seed": "lunar-pulse-35",
    "difficulty": "Hard"
  },
  "2026-06-05": {
    "tiles": [
      1,
      2,
      3,
      4,
      5,
      6,
      7,
      8,
      9
    ],
    "seed": "omega-core-85",
    "difficulty": "Normal"
  },
  "2026-06-06": {
    "tiles": [
      1,
      2,
      3,
      4,
      5,
      6,
      7,
      8,
      9,
      10,
      11,
      12
    ],
    "seed": "omega-moon-19",
    "difficulty": "Hard"
  },
  "2026-06-07": {
    "tiles": [
      1,
      2,
      3,
      4,
      5,
      6,
      7,
      8,
      9
    ],
    "seed": "delta-flux-78",
    "difficulty": "Normal"
  },
  "2026-06-08": {
    "tiles": [
      1,
      2,
      3,
      4,
      5,
      6,
      7,
      8,
      9,
      10,
      11,
      12
    ],
    "seed": "nova-core-83",
    "difficulty": "Hard"
  },
  "2026-06-09": {
    "tiles": [
      1,
      2,
      3,
      4,
      5,
      6,
      7,
      8,
      9
    ],
    "seed": "prime-star-84",
    "difficulty": "Normal"
  },
  "2026-06-10": {
    "tiles": [
      1,
      2,
      3,
      4,
      5,
      6,
      7,
      8,
      9,
      10,
      11,
      12
    ],
    "seed": "prime-core-81",
    "difficulty": "Hard"
  },
  "2026-06-11": {
    "tiles": [
      1,
      2,
      3,
      4,
      5,
      6,
      7,
      8,
      9
    ],
    "seed": "beta-pulse-90",
    "difficulty": "Normal"
  },
  "2026-06-12": {
    "tiles": [
      1,
      2,
      3,
      4,
      5,
      6,
      7,
      8,
      9,
      10,
      11,
      12
    ],
    "seed": "zero-star-80",
    "difficulty": "Hard"
  },
  "2026-06-13": {
    "tiles": [
      1,
      2,
      3,
      4,
      5,
      6,
      7,
      8,
      9
    ],
    "seed": "nova-star-10",
    "difficulty": "Normal"
  },
  "2026-06-14": {
    "tiles": [
      1,
      2,
      3,
      4,
      5,
      6,
      7,
      8,
      9,
      10,
      11,
      12
    ],
    "seed": "omega-node-45",
    "difficulty": "Hard"
  },
  "2026-06-15": {
    "tiles": [
      1,
      2,
      3,
      4,
      5,
      6,
      7,
      8,
      9
    ],
    "seed": "prime-node-22",
    "difficulty": "Normal"
  },
  "2026-06-16": {
    "tiles": [
      1,
      2,
      3,
      4,
      5,
      6,
      7,
      8,
      9,
      10,
      11,
      12
    ],
    "seed": "zero-prime-53",
    "difficulty": "Hard"
  },
  "2026-06-17": {
    "tiles": [
      1,
      2,
      3,
      4,
      5,
      6,
      7,
      8,
      9
    ],
    "seed": "solar-core-56",
    "difficulty": "Normal"
  },
  "2026-06-18": {
    "tiles": [
      1,
      2,
      3,
      4,
      5,
      6,
      7,
      8,
      9,
      10,
      11,
      12
    ],
    "seed": "nova-wave-40",
    "difficulty": "Hard"
  },
  "2026-06-19": {
    "tiles": [
      1,
      2,
      3,
      4,
      5,
      6,
      7,
      8,
      9
    ],
    "seed": "alpha-moon-11",
    "difficulty": "Normal"
  },
  "2026-06-20": {
    "tiles": [
      1,
      2,
      3,
      4,
      5,
      6,
      7,
      8,
      9,
      10,
      11,
      12
    ],
    "seed": "beta-sun-91",
    "difficulty": "Hard"
  },
  "2026-06-21": {
    "tiles": [
      1,
      2,
      3,
      4,
      5,
      6,
      7,
      8,
      9
    ],
    "seed": "prime-star-56",
    "difficulty": "Normal"
  },
  "2026-06-22": {
    "tiles": [
      1,
      2,
      3,
      4,
      5,
      6,
      7,
      8,
      9,
      10,
      11,
      12
    ],
    "seed": "beta-sun-62",
    "difficulty": "Hard"
  },
  "2026-06-23": {
    "tiles": [
      1,
      2,
      3,
      4,
      5,
      6,
      7,
      8,
      9
    ],
    "seed": "gamma-omega-84",
    "difficulty": "Normal"
  },
  "2026-06-24": {
    "tiles": [
      1,
      2,
      3,
      4,
      5,
      6,
      7,
      8,
      9,
      10,
      11,
      12
    ],
    "seed": "solar-star-56",
    "difficulty": "Hard"
  },
  "2026-06-25": {
    "tiles": [
      1,
      2,
      3,
      4,
      5,
      6,
      7,
      8,
      9
    ],
    "seed": "solar-flux-80",
    "difficulty": "Normal"
  },
  "2026-06-26": {
    "tiles": [
      1,
      2,
      3,
      4,
      5,
      6,
      7,
      8,
      9,
      10,
      11,
      12
    ],
    "seed": "prime-pulse-42",
    "difficulty": "Hard"
  },
  "2026-06-27": {
    "tiles": [
      1,
      2,
      3,
      4,
      5,
      6,
      7,
      8,
      9
    ],
    "seed": "prime-prime-76",
    "difficulty": "Normal"
  },
  "2026-06-28": {
    "tiles": [
      1,
      2,
      3,
      4,
      5,
      6,
      7,
      8,
      9,
      10,
      11,
      12
    ],
    "seed": "omega-pulse-87",
    "difficulty": "Hard"
  },
  "2026-06-29": {
    "tiles": [
      1,
      2,
      3,
      4,
      5,
      6,
      7,
      8,
      9
    ],
    "seed": "omega-node-31",
    "difficulty": "Normal"
  },
  "2026-06-30": {
    "tiles": [
      1,
      2,
      3,
      4,
      5,
      6,
      7,
      8,
      9,
      10,
      11,
      12
    ],
    "seed": "gamma-star-68",
    "difficulty": "Hard"
  },
  "2026-07-01": {
    "tiles": [
      1,
      2,
      3,
      4,
      5,
      6,
      7,
      8,
      9
    ],
    "seed": "beta-prime-15",
    "difficulty": "Normal"
  },
  "2026-07-02": {
    "tiles": [
      1,
      2,
      3,
      4,
      5,
      6,
      7,
      8,
      9,
      10,
      11,
      12
    ],
    "seed": "beta-flux-22",
    "difficulty": "Hard"
  },
  "2026-07-03": {
    "tiles": [
      1,
      2,
      3,
      4,
      5,
      6,
      7,
      8,
      9
    ],
    "seed": "nova-sun-70",
    "difficulty": "Normal"
  },
  "2026-07-04": {
    "tiles": [
      1,
      2,
      3,
      4,
      5,
      6,
      7,
      8,
      9,
      10,
      11,
      12
    ],
    "seed": "alpha-prime-29",
    "difficulty": "Hard"
  },
  "2026-07-05": {
    "tiles": [
      1,
      2,
      3,
      4,
      5,
      6,
      7,
      8,
      9
    ],
    "seed": "solar-flux-21",
    "difficulty": "Normal"
  },
  "2026-07-06": {
    "tiles": [
      1,
      2,
      3,
      4,
      5,
      6,
      7,
      8,
      9,
      10,
      11,
      12
    ],
    "seed": "lunar-node-43",
    "difficulty": "Hard"
  },
  "2026-07-07": {
    "tiles": [
      1,
      2,
      3,
      4,
      5,
      6,
      7,
      8,
      9
    ],
    "seed": "delta-star-49",
    "difficulty": "Normal"
  },
  "2026-07-08": {
    "tiles": [
      1,
      2,
      3,
      4,
      5,
      6,
      7,
      8,
      9,
      10,
      11,
      12
    ],
    "seed": "solar-node-26",
    "difficulty": "Hard"
  },
  "2026-07-09": {
    "tiles": [
      1,
      2,
      3,
      4,
      5,
      6,
      7,
      8,
      9
    ],
    "seed": "gamma-wave-47",
    "difficulty": "Normal"
  },
  "2026-07-10": {
    "tiles": [
      1,
      2,
      3,
      4,
      5,
      6,
      7,
      8,
      9,
      10,
      11,
      12
    ],
    "seed": "gamma-moon-15",
    "difficulty": "Hard"
  },
  "2026-07-11": {
    "tiles": [
      1,
      2,
      3,
      4,
      5,
      6,
      7,
      8,
      9
    ],
    "seed": "omega-star-13",
    "difficulty": "Normal"
  },
  "2026-07-12": {
    "tiles": [
      1,
      2,
      3,
      4,
      5,
      6,
      7,
      8,
      9,
      10,
      11,
      12
    ],
    "seed": "gamma-sun-88",
    "difficulty": "Hard"
  },
  "2026-07-13": {
    "tiles": [
      1,
      2,
      3,
      4,
      5,
      6,
      7,
      8,
      9
    ],
    "seed": "omega-pulse-80",
    "difficulty": "Normal"
  },
  "2026-07-14": {
    "tiles": [
      1,
      2,
      3,
      4,
      5,
      6,
      7,
      8,
      9,
      10,
      11,
      12
    ],
    "seed": "prime-pulse-94",
    "difficulty": "Hard"
  },
  "2026-07-15": {
    "tiles": [
      1,
      2,
      3,
      4,
      5,
      6,
      7,
      8,
      9
    ],
    "seed": "alpha-core-58",
    "difficulty": "Normal"
  },
  "2026-07-16": {
    "tiles": [
      1,
      2,
      3,
      4,
      5,
      6,
      7,
      8,
      9,
      10,
      11,
      12
    ],
    "seed": "omega-core-35",
    "difficulty": "Hard"
  },
  "2026-07-17": {
    "tiles": [
      1,
      2,
      3,
      4,
      5,
      6,
      7,
      8,
      9
    ],
    "seed": "prime-node-83",
    "difficulty": "Normal"
  },
  "2026-07-18": {
    "tiles": [
      1,
      2,
      3,
      4,
      5,
      6,
      7,
      8,
      9,
      10,
      11,
      12
    ],
    "seed": "zero-wave-51",
    "difficulty": "Hard"
  },
  "2026-07-19": {
    "tiles": [
      1,
      2,
      3,
      4,
      5,
      6,
      7,
      8,
      9
    ],
    "seed": "alpha-flux-42",
    "difficulty": "Normal"
  },
  "2026-07-20": {
    "tiles": [
      1,
      2,
      3,
      4,
      5,
      6,
      7,
      8,
      9,
      10,
      11,
      12
    ],
    "seed": "gamma-omega-39",
    "difficulty": "Hard"
  },
  "2026-07-21": {
    "tiles": [
      1,
      2,
      3,
      4,
      5,
      6,
      7,
      8,
      9
    ],
    "seed": "omega-sun-79",
    "difficulty": "Normal"
  },
  "2026-07-22": {
    "tiles": [
      1,
      2,
      3,
      4,
      5,
      6,
      7,
      8,
      9,
      10,
      11,
      12
    ],
    "seed": "gamma-star-40",
    "difficulty": "Hard"
  },
  "2026-07-23": {
    "tiles": [
      1,
      2,
      3,
      4,
      5,
      6,
      7,
      8,
      9
    ],
    "seed": "omega-wave-24",
    "difficulty": "Normal"
  },
  "2026-07-24": {
    "tiles": [
      1,
      2,
      3,
      4,
      5,
      6,
      7,
      8,
      9,
      10,
      11,
      12
    ],
    "seed": "solar-core-49",
    "difficulty": "Hard"
  },
  "2026-07-25": {
    "tiles": [
      1,
      2,
      3,
      4,
      5,
      6,
      7,
      8,
      9
    ],
    "seed": "omega-prime-94",
    "difficulty": "Normal"
  },
  "2026-07-26": {
    "tiles": [
      1,
      2,
      3,
      4,
      5,
      6,
      7,
      8,
      9,
      10,
      11,
      12
    ],
    "seed": "gamma-omega-10",
    "difficulty": "Hard"
  },
  "2026-07-27": {
    "tiles": [
      1,
      2,
      3,
      4,
      5,
      6,
      7,
      8,
      9
    ],
    "seed": "gamma-flux-15",
    "difficulty": "Normal"
  },
  "2026-07-28": {
    "tiles": [
      1,
      2,
      3,
      4,
      5,
      6,
      7,
      8,
      9,
      10,
      11,
      12
    ],
    "seed": "solar-pulse-35",
    "difficulty": "Hard"
  },
  "2026-07-29": {
    "tiles": [
      1,
      2,
      3,
      4,
      5,
      6,
      7,
      8,
      9
    ],
    "seed": "beta-moon-56",
    "difficulty": "Normal"
  },
  "2026-07-30": {
    "tiles": [
      1,
      2,
      3,
      4,
      5,
      6,
      7,
      8,
      9,
      10,
      11,
      12
    ],
    "seed": "nova-pulse-44",
    "difficulty": "Hard"
  },
  "2026-07-31": {
    "tiles": [
      1,
      2,
      3,
      4,
      5,
      6,
      7,
      8,
      9
    ],
    "seed": "alpha-pulse-70",
    "difficulty": "Normal"
  },
  "2026-08-01": {
    "tiles": [
      1,
      2,
      3,
      4,
      5,
      6,
      7,
      8,
      9,
      10,
      11,
      12
    ],
    "seed": "prime-core-67",
    "difficulty": "Hard"
  },
  "2026-08-02": {
    "tiles": [
      1,
      2,
      3,
      4,
      5,
      6,
      7,
      8,
      9
    ],
    "seed": "prime-sun-28",
    "difficulty": "Normal"
  },
  "2026-08-03": {
    "tiles": [
      1,
      2,
      3,
      4,
      5,
      6,
      7,
      8,
      9,
      10,
      11,
      12
    ],
    "seed": "prime-omega-81",
    "difficulty": "Hard"
  },
  "2026-08-04": {
    "tiles": [
      1,
      2,
      3,
      4,
      5,
      6,
      7,
      8,
      9
    ],
    "seed": "solar-pulse-44",
    "difficulty": "Normal"
  },
  "2026-08-05": {
    "tiles": [
      1,
      2,
      3,
      4,
      5,
      6,
      7,
      8,
      9,
      10,
      11,
      12
    ],
    "seed": "prime-moon-12",
    "difficulty": "Hard"
  },
  "2026-08-06": {
    "tiles": [
      1,
      2,
      3,
      4,
      5,
      6,
      7,
      8,
      9
    ],
    "seed": "prime-flux-98",
    "difficulty": "Normal"
  },
  "2026-08-07": {
    "tiles": [
      1,
      2,
      3,
      4,
      5,
      6,
      7,
      8,
      9,
      10,
      11,
      12
    ],
    "seed": "zero-wave-98",
    "difficulty": "Hard"
  },
  "2026-08-08": {
    "tiles": [
      1,
      2,
      3,
      4,
      5,
      6,
      7,
      8,
      9
    ],
    "seed": "gamma-wave-17",
    "difficulty": "Normal"
  },
  "2026-08-09": {
    "tiles": [
      1,
      2,
      3,
      4,
      5,
      6,
      7,
      8,
      9,
      10,
      11,
      12
    ],
    "seed": "delta-star-32",
    "difficulty": "Hard"
  },
  "2026-08-10": {
    "tiles": [
      1,
      2,
      3,
      4,
      5,
      6,
      7,
      8,
      9
    ],
    "seed": "zero-flux-24",
    "difficulty": "Normal"
  },
  "2026-08-11": {
    "tiles": [
      1,
      2,
      3,
      4,
      5,
      6,
      7,
      8,
      9,
      10,
      11,
      12
    ],
    "seed": "gamma-node-10",
    "difficulty": "Hard"
  },
  "2026-08-12": {
    "tiles": [
      1,
      2,
      3,
      4,
      5,
      6,
      7,
      8,
      9
    ],
    "seed": "nova-prime-10",
    "difficulty": "Normal"
  },
  "2026-08-13": {
    "tiles": [
      1,
      2,
      3,
      4,
      5,
      6,
      7,
      8,
      9,
      10,
      11,
      12
    ],
    "seed": "gamma-omega-79",
    "difficulty": "Hard"
  },
  "2026-08-14": {
    "tiles": [
      1,
      2,
      3,
      4,
      5,
      6,
      7,
      8,
      9
    ],
    "seed": "solar-omega-51",
    "difficulty": "Normal"
  },
  "2026-08-15": {
    "tiles": [
      1,
      2,
      3,
      4,
      5,
      6,
      7,
      8,
      9,
      10,
      11,
      12
    ],
    "seed": "lunar-sun-63",
    "difficulty": "Hard"
  },
  "2026-08-16": {
    "tiles": [
      1,
      2,
      3,
      4,
      5,
      6,
      7,
      8,
      9
    ],
    "seed": "zero-pulse-97",
    "difficulty": "Normal"
  },
  "2026-08-17": {
    "tiles": [
      1,
      2,
      3,
      4,
      5,
      6,
      7,
      8,
      9,
      10,
      11,
      12
    ],
    "seed": "zero-pulse-78",
    "difficulty": "Hard"
  },
  "2026-08-18": {
    "tiles": [
      1,
      2,
      3,
      4,
      5,
      6,
      7,
      8,
      9
    ],
    "seed": "delta-star-38",
    "difficulty": "Normal"
  },
  "2026-08-19": {
    "tiles": [
      1,
      2,
      3,
      4,
      5,
      6,
      7,
      8,
      9,
      10,
      11,
      12
    ],
    "seed": "alpha-moon-97",
    "difficulty": "Hard"
  },
  "2026-08-20": {
    "tiles": [
      1,
      2,
      3,
      4,
      5,
      6,
      7,
      8,
      9
    ],
    "seed": "nova-pulse-13",
    "difficulty": "Normal"
  },
  "2026-08-21": {
    "tiles": [
      1,
      2,
      3,
      4,
      5,
      6,
      7,
      8,
      9,
      10,
      11,
      12
    ],
    "seed": "lunar-node-72",
    "difficulty": "Hard"
  },
  "2026-08-22": {
    "tiles": [
      1,
      2,
      3,
      4,
      5,
      6,
      7,
      8,
      9
    ],
    "seed": "nova-sun-14",
    "difficulty": "Normal"
  },
  "2026-08-23": {
    "tiles": [
      1,
      2,
      3,
      4,
      5,
      6,
      7,
      8,
      9,
      10,
      11,
      12
    ],
    "seed": "solar-wave-30",
    "difficulty": "Hard"
  },
  "2026-08-24": {
    "tiles": [
      1,
      2,
      3,
      4,
      5,
      6,
      7,
      8,
      9
    ],
    "seed": "beta-flux-74",
    "difficulty": "Normal"
  },
  "2026-08-25": {
    "tiles": [
      1,
      2,
      3,
      4,
      5,
      6,
      7,
      8,
      9,
      10,
      11,
      12
    ],
    "seed": "solar-omega-84",
    "difficulty": "Hard"
  },
  "2026-08-26": {
    "tiles": [
      1,
      2,
      3,
      4,
      5,
      6,
      7,
      8,
      9
    ],
    "seed": "beta-pulse-14",
    "difficulty": "Normal"
  },
  "2026-08-27": {
    "tiles": [
      1,
      2,
      3,
      4,
      5,
      6,
      7,
      8,
      9,
      10,
      11,
      12
    ],
    "seed": "gamma-prime-40",
    "difficulty": "Hard"
  },
  "2026-08-28": {
    "tiles": [
      1,
      2,
      3,
      4,
      5,
      6,
      7,
      8,
      9
    ],
    "seed": "omega-prime-88",
    "difficulty": "Normal"
  },
  "2026-08-29": {
    "tiles": [
      1,
      2,
      3,
      4,
      5,
      6,
      7,
      8,
      9,
      10,
      11,
      12
    ],
    "seed": "prime-prime-76",
    "difficulty": "Hard"
  },
  "2026-08-30": {
    "tiles": [
      1,
      2,
      3,
      4,
      5,
      6,
      7,
      8,
      9
    ],
    "seed": "beta-moon-19",
    "difficulty": "Normal"
  },
  "2026-08-31": {
    "tiles": [
      1,
      2,
      3,
      4,
      5,
      6,
      7,
      8,
      9,
      10,
      11,
      12
    ],
    "seed": "omega-omega-67",
    "difficulty": "Hard"
  },
  "2026-09-01": {
    "tiles": [
      1,
      2,
      3,
      4,
      5,
      6,
      7,
      8,
      9
    ],
    "seed": "alpha-pulse-34",
    "difficulty": "Normal"
  },
  "2026-09-02": {
    "tiles": [
      1,
      2,
      3,
      4,
      5,
      6,
      7,
      8,
      9,
      10,
      11,
      12
    ],
    "seed": "prime-pulse-68",
    "difficulty": "Hard"
  },
  "2026-09-03": {
    "tiles": [
      1,
      2,
      3,
      4,
      5,
      6,
      7,
      8,
      9
    ],
    "seed": "zero-flux-60",
    "difficulty": "Normal"
  },
  "2026-09-04": {
    "tiles": [
      1,
      2,
      3,
      4,
      5,
      6,
      7,
      8,
      9,
      10,
      11,
      12
    ],
    "seed": "solar-omega-59",
    "difficulty": "Hard"
  },
  "2026-09-05": {
    "tiles": [
      1,
      2,
      3,
      4,
      5,
      6,
      7,
      8,
      9
    ],
    "seed": "delta-pulse-60",
    "difficulty": "Normal"
  },
  "2026-09-06": {
    "tiles": [
      1,
      2,
      3,
      4,
      5,
      6,
      7,
      8,
      9,
      10,
      11,
      12
    ],
    "seed": "beta-moon-69",
    "difficulty": "Hard"
  },
  "2026-09-07": {
    "tiles": [
      1,
      2,
      3,
      4,
      5,
      6,
      7,
      8,
      9
    ],
    "seed": "solar-moon-63",
    "difficulty": "Normal"
  },
  "2026-09-08": {
    "tiles": [
      1,
      2,
      3,
      4,
      5,
      6,
      7,
      8,
      9,
      10,
      11,
      12
    ],
    "seed": "lunar-wave-64",
    "difficulty": "Hard"
  },
  "2026-09-09": {
    "tiles": [
      1,
      2,
      3,
      4,
      5,
      6,
      7,
      8,
      9
    ],
    "seed": "nova-prime-95",
    "difficulty": "Normal"
  },
  "2026-09-10": {
    "tiles": [
      1,
      2,
      3,
      4,
      5,
      6,
      7,
      8,
      9,
      10,
      11,
      12
    ],
    "seed": "gamma-omega-46",
    "difficulty": "Hard"
  },
  "2026-09-11": {
    "tiles": [
      1,
      2,
      3,
      4,
      5,
      6,
      7,
      8,
      9
    ],
    "seed": "solar-star-16",
    "difficulty": "Normal"
  },
  "2026-09-12": {
    "tiles": [
      1,
      2,
      3,
      4,
      5,
      6,
      7,
      8,
      9,
      10,
      11,
      12
    ],
    "seed": "omega-node-83",
    "difficulty": "Hard"
  },
  "2026-09-13": {
    "tiles": [
      1,
      2,
      3,
      4,
      5,
      6,
      7,
      8,
      9
    ],
    "seed": "alpha-omega-81",
    "difficulty": "Normal"
  },
  "2026-09-14": {
    "tiles": [
      1,
      2,
      3,
      4,
      5,
      6,
      7,
      8,
      9,
      10,
      11,
      12
    ],
    "seed": "alpha-flux-28",
    "difficulty": "Hard"
  },
  "2026-09-15": {
    "tiles": [
      1,
      2,
      3,
      4,
      5,
      6,
      7,
      8,
      9
    ],
    "seed": "alpha-pulse-93",
    "difficulty": "Normal"
  },
  "2026-09-16": {
    "tiles": [
      1,
      2,
      3,
      4,
      5,
      6,
      7,
      8,
      9,
      10,
      11,
      12
    ],
    "seed": "beta-node-13",
    "difficulty": "Hard"
  },
  "2026-09-17": {
    "tiles": [
      1,
      2,
      3,
      4,
      5,
      6,
      7,
      8,
      9
    ],
    "seed": "gamma-prime-83",
    "difficulty": "Normal"
  },
  "2026-09-18": {
    "tiles": [
      1,
      2,
      3,
      4,
      5,
      6,
      7,
      8,
      9,
      10,
      11,
      12
    ],
    "seed": "omega-omega-80",
    "difficulty": "Hard"
  },
  "2026-09-19": {
    "tiles": [
      1,
      2,
      3,
      4,
      5,
      6,
      7,
      8,
      9
    ],
    "seed": "zero-wave-13",
    "difficulty": "Normal"
  },
  "2026-09-20": {
    "tiles": [
      1,
      2,
      3,
      4,
      5,
      6,
      7,
      8,
      9,
      10,
      11,
      12
    ],
    "seed": "prime-wave-51",
    "difficulty": "Hard"
  },
  "2026-09-21": {
    "tiles": [
      1,
      2,
      3,
      4,
      5,
      6,
      7,
      8,
      9
    ],
    "seed": "gamma-flux-18",
    "difficulty": "Normal"
  },
  "2026-09-22": {
    "tiles": [
      1,
      2,
      3,
      4,
      5,
      6,
      7,
      8,
      9,
      10,
      11,
      12
    ],
    "seed": "omega-moon-33",
    "difficulty": "Hard"
  },
  "2026-09-23": {
    "tiles": [
      1,
      2,
      3,
      4,
      5,
      6,
      7,
      8,
      9
    ],
    "seed": "gamma-node-56",
    "difficulty": "Normal"
  },
  "2026-09-24": {
    "tiles": [
      1,
      2,
      3,
      4,
      5,
      6,
      7,
      8,
      9,
      10,
      11,
      12
    ],
    "seed": "alpha-prime-29",
    "difficulty": "Hard"
  },
  "2026-09-25": {
    "tiles": [
      1,
      2,
      3,
      4,
      5,
      6,
      7,
      8,
      9
    ],
    "seed": "beta-omega-90",
    "difficulty": "Normal"
  },
  "2026-09-26": {
    "tiles": [
      1,
      2,
      3,
      4,
      5,
      6,
      7,
      8,
      9,
      10,
      11,
      12
    ],
    "seed": "omega-wave-38",
    "difficulty": "Hard"
  },
  "2026-09-27": {
    "tiles": [
      1,
      2,
      3,
      4,
      5,
      6,
      7,
      8,
      9
    ],
    "seed": "delta-node-62",
    "difficulty": "Normal"
  },
  "2026-09-28": {
    "tiles": [
      1,
      2,
      3,
      4,
      5,
      6,
      7,
      8,
      9,
      10,
      11,
      12
    ],
    "seed": "gamma-pulse-24",
    "difficulty": "Hard"
  },
  "2026-09-29": {
    "tiles": [
      1,
      2,
      3,
      4,
      5,
      6,
      7,
      8,
      9
    ],
    "seed": "omega-prime-82",
    "difficulty": "Normal"
  },
  "2026-09-30": {
    "tiles": [
      1,
      2,
      3,
      4,
      5,
      6,
      7,
      8,
      9,
      10,
      11,
      12
    ],
    "seed": "solar-sun-99",
    "difficulty": "Hard"
  },
  "2026-10-01": {
    "tiles": [
      1,
      2,
      3,
      4,
      5,
      6,
      7,
      8,
      9
    ],
    "seed": "beta-wave-34",
    "difficulty": "Normal"
  },
  "2026-10-02": {
    "tiles": [
      1,
      2,
      3,
      4,
      5,
      6,
      7,
      8,
      9,
      10,
      11,
      12
    ],
    "seed": "lunar-omega-44",
    "difficulty": "Hard"
  },
  "2026-10-03": {
    "tiles": [
      1,
      2,
      3,
      4,
      5,
      6,
      7,
      8,
      9
    ],
    "seed": "omega-omega-72",
    "difficulty": "Normal"
  },
  "2026-10-04": {
    "tiles": [
      1,
      2,
      3,
      4,
      5,
      6,
      7,
      8,
      9,
      10,
      11,
      12
    ],
    "seed": "gamma-wave-11",
    "difficulty": "Hard"
  },
  "2026-10-05": {
    "tiles": [
      1,
      2,
      3,
      4,
      5,
      6,
      7,
      8,
      9
    ],
    "seed": "alpha-core-38",
    "difficulty": "Normal"
  },
  "2026-10-06": {
    "tiles": [
      1,
      2,
      3,
      4,
      5,
      6,
      7,
      8,
      9,
      10,
      11,
      12
    ],
    "seed": "alpha-pulse-18",
    "difficulty": "Hard"
  },
  "2026-10-07": {
    "tiles": [
      1,
      2,
      3,
      4,
      5,
      6,
      7,
      8,
      9
    ],
    "seed": "delta-sun-12",
    "difficulty": "Normal"
  },
  "2026-10-08": {
    "tiles": [
      1,
      2,
      3,
      4,
      5,
      6,
      7,
      8,
      9,
      10,
      11,
      12
    ],
    "seed": "lunar-sun-63",
    "difficulty": "Hard"
  },
  "2026-10-09": {
    "tiles": [
      1,
      2,
      3,
      4,
      5,
      6,
      7,
      8,
      9
    ],
    "seed": "beta-moon-19",
    "difficulty": "Normal"
  },
  "2026-10-10": {
    "tiles": [
      1,
      2,
      3,
      4,
      5,
      6,
      7,
      8,
      9,
      10,
      11,
      12
    ],
    "seed": "beta-star-57",
    "difficulty": "Hard"
  },
  "2026-10-11": {
    "tiles": [
      1,
      2,
      3,
      4,
      5,
      6,
      7,
      8,
      9
    ],
    "seed": "zero-flux-14",
    "difficulty": "Normal"
  },
  "2026-10-12": {
    "tiles": [
      1,
      2,
      3,
      4,
      5,
      6,
      7,
      8,
      9,
      10,
      11,
      12
    ],
    "seed": "lunar-core-33",
    "difficulty": "Hard"
  },
  "2026-10-13": {
    "tiles": [
      1,
      2,
      3,
      4,
      5,
      6,
      7,
      8,
      9
    ],
    "seed": "prime-wave-56",
    "difficulty": "Normal"
  },
  "2026-10-14": {
    "tiles": [
      1,
      2,
      3,
      4,
      5,
      6,
      7,
      8,
      9,
      10,
      11,
      12
    ],
    "seed": "alpha-wave-50",
    "difficulty": "Hard"
  },
  "2026-10-15": {
    "tiles": [
      1,
      2,
      3,
      4,
      5,
      6,
      7,
      8,
      9
    ],
    "seed": "lunar-core-75",
    "difficulty": "Normal"
  },
  "2026-10-16": {
    "tiles": [
      1,
      2,
      3,
      4,
      5,
      6,
      7,
      8,
      9,
      10,
      11,
      12
    ],
    "seed": "nova-flux-63",
    "difficulty": "Hard"
  },
  "2026-10-17": {
    "tiles": [
      1,
      2,
      3,
      4,
      5,
      6,
      7,
      8,
      9
    ],
    "seed": "lunar-moon-40",
    "difficulty": "Normal"
  },
  "2026-10-18": {
    "tiles": [
      1,
      2,
      3,
      4,
      5,
      6,
      7,
      8,
      9,
      10,
      11,
      12
    ],
    "seed": "solar-omega-93",
    "difficulty": "Hard"
  },
  "2026-10-19": {
    "tiles": [
      1,
      2,
      3,
      4,
      5,
      6,
      7,
      8,
      9
    ],
    "seed": "beta-moon-49",
    "difficulty": "Normal"
  },
  "2026-10-20": {
    "tiles": [
      1,
      2,
      3,
      4,
      5,
      6,
      7,
      8,
      9,
      10,
      11,
      12
    ],
    "seed": "omega-moon-58",
    "difficulty": "Hard"
  },
  "2026-10-21": {
    "tiles": [
      1,
      2,
      3,
      4,
      5,
      6,
      7,
      8,
      9
    ],
    "seed": "delta-moon-23",
    "difficulty": "Normal"
  },
  "2026-10-22": {
    "tiles": [
      1,
      2,
      3,
      4,
      5,
      6,
      7,
      8,
      9,
      10,
      11,
      12
    ],
    "seed": "delta-prime-29",
    "difficulty": "Hard"
  },
  "2026-10-23": {
    "tiles": [
      1,
      2,
      3,
      4,
      5,
      6,
      7,
      8,
      9
    ],
    "seed": "lunar-pulse-56",
    "difficulty": "Normal"
  },
  "2026-10-24": {
    "tiles": [
      1,
      2,
      3,
      4,
      5,
      6,
      7,
      8,
      9,
      10,
      11,
      12
    ],
    "seed": "beta-pulse-45",
    "difficulty": "Hard"
  },
  "2026-10-25": {
    "tiles": [
      1,
      2,
      3,
      4,
      5,
      6,
      7,
      8,
      9
    ],
    "seed": "omega-sun-12",
    "difficulty": "Normal"
  },
  "2026-10-26": {
    "tiles": [
      1,
      2,
      3,
      4,
      5,
      6,
      7,
      8,
      9,
      10,
      11,
      12
    ],
    "seed": "beta-moon-24",
    "difficulty": "Hard"
  },
  "2026-10-27": {
    "tiles": [
      1,
      2,
      3,
      4,
      5,
      6,
      7,
      8,
      9
    ],
    "seed": "omega-sun-86",
    "difficulty": "Normal"
  },
  "2026-10-28": {
    "tiles": [
      1,
      2,
      3,
      4,
      5,
      6,
      7,
      8,
      9,
      10,
      11,
      12
    ],
    "seed": "delta-prime-96",
    "difficulty": "Hard"
  },
  "2026-10-29": {
    "tiles": [
      1,
      2,
      3,
      4,
      5,
      6,
      7,
      8,
      9
    ],
    "seed": "lunar-moon-40",
    "difficulty": "Normal"
  },
  "2026-10-30": {
    "tiles": [
      1,
      2,
      3,
      4,
      5,
      6,
      7,
      8,
      9,
      10,
      11,
      12
    ],
    "seed": "prime-pulse-75",
    "difficulty": "Hard"
  },
  "2026-10-31": {
    "tiles": [
      1,
      2,
      3,
      4,
      5,
      6,
      7,
      8,
      9
    ],
    "seed": "solar-prime-37",
    "difficulty": "Normal"
  },
  "2026-11-01": {
    "tiles": [
      1,
      2,
      3,
      4,
      5,
      6,
      7,
      8,
      9,
      10,
      11,
      12
    ],
    "seed": "zero-pulse-52",
    "difficulty": "Hard"
  },
  "2026-11-02": {
    "tiles": [
      1,
      2,
      3,
      4,
      5,
      6,
      7,
      8,
      9
    ],
    "seed": "alpha-omega-89",
    "difficulty": "Normal"
  },
  "2026-11-03": {
    "tiles": [
      1,
      2,
      3,
      4,
      5,
      6,
      7,
      8,
      9,
      10,
      11,
      12
    ],
    "seed": "gamma-prime-64",
    "difficulty": "Hard"
  },
  "2026-11-04": {
    "tiles": [
      1,
      2,
      3,
      4,
      5,
      6,
      7,
      8,
      9
    ],
    "seed": "beta-omega-12",
    "difficulty": "Normal"
  },
  "2026-11-05": {
    "tiles": [
      1,
      2,
      3,
      4,
      5,
      6,
      7,
      8,
      9,
      10,
      11,
      12
    ],
    "seed": "zero-star-45",
    "difficulty": "Hard"
  },
  "2026-11-06": {
    "tiles": [
      1,
      2,
      3,
      4,
      5,
      6,
      7,
      8,
      9
    ],
    "seed": "nova-flux-25",
    "difficulty": "Normal"
  },
  "2026-11-07": {
    "tiles": [
      1,
      2,
      3,
      4,
      5,
      6,
      7,
      8,
      9,
      10,
      11,
      12
    ],
    "seed": "gamma-prime-98",
    "difficulty": "Hard"
  },
  "2026-11-08": {
    "tiles": [
      1,
      2,
      3,
      4,
      5,
      6,
      7,
      8,
      9
    ],
    "seed": "zero-flux-20",
    "difficulty": "Normal"
  },
  "2026-11-09": {
    "tiles": [
      1,
      2,
      3,
      4,
      5,
      6,
      7,
      8,
      9,
      10,
      11,
      12
    ],
    "seed": "beta-omega-84",
    "difficulty": "Hard"
  },
  "2026-11-10": {
    "tiles": [
      1,
      2,
      3,
      4,
      5,
      6,
      7,
      8,
      9
    ],
    "seed": "prime-star-68",
    "difficulty": "Normal"
  },
  "2026-11-11": {
    "tiles": [
      1,
      2,
      3,
      4,
      5,
      6,
      7,
      8,
      9,
      10,
      11,
      12
    ],
    "seed": "nova-star-15",
    "difficulty": "Hard"
  },
  "2026-11-12": {
    "tiles": [
      1,
      2,
      3,
      4,
      5,
      6,
      7,
      8,
      9
    ],
    "seed": "beta-omega-64",
    "difficulty": "Normal"
  },
  "2026-11-13": {
    "tiles": [
      1,
      2,
      3,
      4,
      5,
      6,
      7,
      8,
      9,
      10,
      11,
      12
    ],
    "seed": "omega-wave-28",
    "difficulty": "Hard"
  },
  "2026-11-14": {
    "tiles": [
      1,
      2,
      3,
      4,
      5,
      6,
      7,
      8,
      9
    ],
    "seed": "lunar-star-87",
    "difficulty": "Normal"
  },
  "2026-11-15": {
    "tiles": [
      1,
      2,
      3,
      4,
      5,
      6,
      7,
      8,
      9,
      10,
      11,
      12
    ],
    "seed": "prime-pulse-94",
    "difficulty": "Hard"
  },
  "2026-11-16": {
    "tiles": [
      1,
      2,
      3,
      4,
      5,
      6,
      7,
      8,
      9
    ],
    "seed": "prime-node-33",
    "difficulty": "Normal"
  },
  "2026-11-17": {
    "tiles": [
      1,
      2,
      3,
      4,
      5,
      6,
      7,
      8,
      9,
      10,
      11,
      12
    ],
    "seed": "gamma-prime-64",
    "difficulty": "Hard"
  },
  "2026-11-18": {
    "tiles": [
      1,
      2,
      3,
      4,
      5,
      6,
      7,
      8,
      9
    ],
    "seed": "solar-core-56",
    "difficulty": "Normal"
  },
  "2026-11-19": {
    "tiles": [
      1,
      2,
      3,
      4,
      5,
      6,
      7,
      8,
      9,
      10,
      11,
      12
    ],
    "seed": "delta-wave-66",
    "difficulty": "Hard"
  },
  "2026-11-20": {
    "tiles": [
      1,
      2,
      3,
      4,
      5,
      6,
      7,
      8,
      9
    ],
    "seed": "nova-wave-92",
    "difficulty": "Normal"
  },
  "2026-11-21": {
    "tiles": [
      1,
      2,
      3,
      4,
      5,
      6,
      7,
      8,
      9,
      10,
      11,
      12
    ],
    "seed": "prime-star-81",
    "difficulty": "Hard"
  },
  "2026-11-22": {
    "tiles": [
      1,
      2,
      3,
      4,
      5,
      6,
      7,
      8,
      9
    ],
    "seed": "beta-sun-41",
    "difficulty": "Normal"
  },
  "2026-11-23": {
    "tiles": [
      1,
      2,
      3,
      4,
      5,
      6,
      7,
      8,
      9,
      10,
      11,
      12
    ],
    "seed": "nova-moon-89",
    "difficulty": "Hard"
  },
  "2026-11-24": {
    "tiles": [
      1,
      2,
      3,
      4,
      5,
      6,
      7,
      8,
      9
    ],
    "seed": "zero-core-51",
    "difficulty": "Normal"
  },
  "2026-11-25": {
    "tiles": [
      1,
      2,
      3,
      4,
      5,
      6,
      7,
      8,
      9,
      10,
      11,
      12
    ],
    "seed": "omega-moon-89",
    "difficulty": "Hard"
  },
  "2026-11-26": {
    "tiles": [
      1,
      2,
      3,
      4,
      5,
      6,
      7,
      8,
      9
    ],
    "seed": "prime-moon-21",
    "difficulty": "Normal"
  },
  "2026-11-27": {
    "tiles": [
      1,
      2,
      3,
      4,
      5,
      6,
      7,
      8,
      9,
      10,
      11,
      12
    ],
    "seed": "beta-node-17",
    "difficulty": "Hard"
  },
  "2026-11-28": {
    "tiles": [
      1,
      2,
      3,
      4,
      5,
      6,
      7,
      8,
      9
    ],
    "seed": "nova-pulse-66",
    "difficulty": "Normal"
  },
  "2026-11-29": {
    "tiles": [
      1,
      2,
      3,
      4,
      5,
      6,
      7,
      8,
      9,
      10,
      11,
      12
    ],
    "seed": "solar-wave-43",
    "difficulty": "Hard"
  },
  "2026-11-30": {
    "tiles": [
      1,
      2,
      3,
      4,
      5,
      6,
      7,
      8,
      9
    ],
    "seed": "omega-prime-52",
    "difficulty": "Normal"
  },
  "2026-12-01": {
    "tiles": [
      1,
      2,
      3,
      4,
      5,
      6,
      7,
      8,
      9,
      10,
      11,
      12
    ],
    "seed": "alpha-wave-71",
    "difficulty": "Hard"
  },
  "2026-12-02": {
    "tiles": [
      1,
      2,
      3,
      4,
      5,
      6,
      7,
      8,
      9
    ],
    "seed": "prime-pulse-89",
    "difficulty": "Normal"
  },
  "2026-12-03": {
    "tiles": [
      1,
      2,
      3,
      4,
      5,
      6,
      7,
      8,
      9,
      10,
      11,
      12
    ],
    "seed": "zero-node-85",
    "difficulty": "Hard"
  },
  "2026-12-04": {
    "tiles": [
      1,
      2,
      3,
      4,
      5,
      6,
      7,
      8,
      9
    ],
    "seed": "gamma-flux-44",
    "difficulty": "Normal"
  },
  "2026-12-05": {
    "tiles": [
      1,
      2,
      3,
      4,
      5,
      6,
      7,
      8,
      9,
      10,
      11,
      12
    ],
    "seed": "prime-sun-86",
    "difficulty": "Hard"
  },
  "2026-12-06": {
    "tiles": [
      1,
      2,
      3,
      4,
      5,
      6,
      7,
      8,
      9
    ],
    "seed": "solar-sun-77",
    "difficulty": "Normal"
  },
  "2026-12-07": {
    "tiles": [
      1,
      2,
      3,
      4,
      5,
      6,
      7,
      8,
      9,
      10,
      11,
      12
    ],
    "seed": "beta-flux-17",
    "difficulty": "Hard"
  },
  "2026-12-08": {
    "tiles": [
      1,
      2,
      3,
      4,
      5,
      6,
      7,
      8,
      9
    ],
    "seed": "prime-wave-39",
    "difficulty": "Normal"
  },
  "2026-12-09": {
    "tiles": [
      1,
      2,
      3,
      4,
      5,
      6,
      7,
      8,
      9,
      10,
      11,
      12
    ],
    "seed": "nova-pulse-93",
    "difficulty": "Hard"
  },
  "2026-12-10": {
    "tiles": [
      1,
      2,
      3,
      4,
      5,
      6,
      7,
      8,
      9
    ],
    "seed": "nova-star-30",
    "difficulty": "Normal"
  },
  "2026-12-11": {
    "tiles": [
      1,
      2,
      3,
      4,
      5,
      6,
      7,
      8,
      9,
      10,
      11,
      12
    ],
    "seed": "nova-wave-18",
    "difficulty": "Hard"
  },
  "2026-12-12": {
    "tiles": [
      1,
      2,
      3,
      4,
      5,
      6,
      7,
      8,
      9
    ],
    "seed": "gamma-moon-42",
    "difficulty": "Normal"
  },
  "2026-12-13": {
    "tiles": [
      1,
      2,
      3,
      4,
      5,
      6,
      7,
      8,
      9,
      10,
      11,
      12
    ],
    "seed": "omega-moon-33",
    "difficulty": "Hard"
  },
  "2026-12-14": {
    "tiles": [
      1,
      2,
      3,
      4,
      5,
      6,
      7,
      8,
      9
    ],
    "seed": "alpha-flux-68",
    "difficulty": "Normal"
  },
  "2026-12-15": {
    "tiles": [
      1,
      2,
      3,
      4,
      5,
      6,
      7,
      8,
      9,
      10,
      11,
      12
    ],
    "seed": "alpha-sun-40",
    "difficulty": "Hard"
  },
  "2026-12-16": {
    "tiles": [
      1,
      2,
      3,
      4,
      5,
      6,
      7,
      8,
      9
    ],
    "seed": "lunar-node-54",
    "difficulty": "Normal"
  },
  "2026-12-17": {
    "tiles": [
      1,
      2,
      3,
      4,
      5,
      6,
      7,
      8,
      9,
      10,
      11,
      12
    ],
    "seed": "beta-core-74",
    "difficulty": "Hard"
  },
  "2026-12-18": {
    "tiles": [
      1,
      2,
      3,
      4,
      5,
      6,
      7,
      8,
      9
    ],
    "seed": "alpha-flux-71",
    "difficulty": "Normal"
  },
  "2026-12-19": {
    "tiles": [
      1,
      2,
      3,
      4,
      5,
      6,
      7,
      8,
      9,
      10,
      11,
      12
    ],
    "seed": "alpha-wave-74",
    "difficulty": "Hard"
  },
  "2026-12-20": {
    "tiles": [
      1,
      2,
      3,
      4,
      5,
      6,
      7,
      8,
      9
    ],
    "seed": "gamma-wave-19",
    "difficulty": "Normal"
  },
  "2026-12-21": {
    "tiles": [
      1,
      2,
      3,
      4,
      5,
      6,
      7,
      8,
      9,
      10,
      11,
      12
    ],
    "seed": "lunar-sun-69",
    "difficulty": "Hard"
  },
  "2026-12-22": {
    "tiles": [
      1,
      2,
      3,
      4,
      5,
      6,
      7,
      8,
      9
    ],
    "seed": "alpha-omega-12",
    "difficulty": "Normal"
  },
  "2026-12-23": {
    "tiles": [
      1,
      2,
      3,
      4,
      5,
      6,
      7,
      8,
      9,
      10,
      11,
      12
    ],
    "seed": "omega-prime-83",
    "difficulty": "Hard"
  },
  "2026-12-24": {
    "tiles": [
      1,
      2,
      3,
      4,
      5,
      6,
      7,
      8,
      9
    ],
    "seed": "nova-sun-97",
    "difficulty": "Normal"
  },
  "2026-12-25": {
    "tiles": [
      1,
      2,
      3,
      4,
      5,
      6,
      7,
      8,
      9,
      10,
      11,
      12
    ],
    "seed": "solar-omega-69",
    "difficulty": "Hard"
  },
  "2026-12-26": {
    "tiles": [
      1,
      2,
      3,
      4,
      5,
      6,
      7,
      8,
      9
    ],
    "seed": "omega-prime-93",
    "difficulty": "Normal"
  },
  "2026-12-27": {
    "tiles": [
      1,
      2,
      3,
      4,
      5,
      6,
      7,
      8,
      9,
      10,
      11,
      12
    ],
    "seed": "lunar-prime-68",
    "difficulty": "Hard"
  },
  "2026-12-28": {
    "tiles": [
      1,
      2,
      3,
      4,
      5,
      6,
      7,
      8,
      9
    ],
    "seed": "zero-core-96",
    "difficulty": "Normal"
  },
  "2026-12-29": {
    "tiles": [
      1,
      2,
      3,
      4,
      5,
      6,
      7,
      8,
      9,
      10,
      11,
      12
    ],
    "seed": "solar-prime-65",
    "difficulty": "Hard"
  },
  "2026-12-30": {
    "tiles": [
      1,
      2,
      3,
      4,
      5,
      6,
      7,
      8,
      9
    ],
    "seed": "solar-wave-22",
    "difficulty": "Normal"
  },
  "2026-12-31": {
    "tiles": [
      1,
      2,
      3,
      4,
      5,
      6,
      7,
      8,
      9,
      10,
      11,
      12
    ],
    "seed": "nova-star-50",
    "difficulty": "Hard"
  }
}